restore_commit_times.py
restore_commit_times-0.5.dist-info/DESCRIPTION.rst
restore_commit_times-0.5.dist-info/METADATA
restore_commit_times-0.5.dist-info/RECORD
restore_commit_times-0.5.dist-info/WHEEL
restore_commit_times-0.5.dist-info/entry_points.txt
restore_commit_times-0.5.dist-info/metadata.json
restore_commit_times-0.5.dist-info/top_level.txt
